<?xml version="1.0" encoding="UTF-8"?><record_update table="sp_instance">
    <sp_instance action="INSERT_OR_UPDATE">
        <active>true</active>
        <class_name/>
        <color>default</color>
        <css/>
        <glyph/>
        <id/>
        <order>1</order>
        <roles/>
        <short_description/>
        <size>md</size>
        <sp_column display_value="2">28efe9426fda4300218117164b3ee45d</sp_column>
        <sp_widget display_value="PEX - Planos de ação Lista">9dfe94e96f1a03001fb18a6d6b3ee423</sp_widget>
        <sys_class_name>sp_instance</sys_class_name>
        <sys_created_by>victor.leite</sys_created_by>
        <sys_created_on>2017-11-07 16:41:35</sys_created_on>
        <sys_customer_update>false</sys_customer_update>
        <sys_id>c60fd06d6f1a03001fb18a6d6b3ee434</sys_id>
        <sys_mod_count>15</sys_mod_count>
        <sys_name>Planos de ação</sys_name>
        <sys_package display_value="PEX" source="x_alabs_pex">4a94483c6f0a8f841fb18a6d6b3ee494</sys_package>
        <sys_policy/>
        <sys_replace_on_upgrade>false</sys_replace_on_upgrade>
        <sys_scope display_value="PEX">4a94483c6f0a8f841fb18a6d6b3ee494</sys_scope>
        <sys_update_name>sp_instance_c60fd06d6f1a03001fb18a6d6b3ee434</sys_update_name>
        <sys_updated_by>alparservice.marcos</sys_updated_by>
        <sys_updated_on>2018-10-29 17:02:35</sys_updated_on>
        <title>Planos de ação</title>
        <url/>
        <widget_parameters><![CDATA[{
	"filtro": {
		"value": "state=pending",
		"displayValue": "state=pending"
	},
	"mostrar_tudo": {
		"value": "true",
		"displayValue": "true"
	},
	"maximo": {
		"value": 6,
		"displayValue": "6"
	}
}]]></widget_parameters>
    </sp_instance>
</record_update>
